MANIFEST.in
README.rst
setup.py
urp.py
urp.egg-info/PKG-INFO
urp.egg-info/SOURCES.txt
urp.egg-info/dependency_links.txt
urp.egg-info/entry_points.txt
urp.egg-info/not-zip-safe
urp.egg-info/top_level.txt